sphinx_wagtail_theme/__init__.py
sphinx_wagtail_theme/breadcrumbs.html
sphinx_wagtail_theme/domainindex.html
sphinx_wagtail_theme/extensions.html
sphinx_wagtail_theme/footer.html
sphinx_wagtail_theme/genindex-single.html
sphinx_wagtail_theme/genindex-split.html
sphinx_wagtail_theme/genindex.html
sphinx_wagtail_theme/globaltoc.html
sphinx_wagtail_theme/layout.html
sphinx_wagtail_theme/page.html
sphinx_wagtail_theme/pager.html
sphinx_wagtail_theme/search.html
sphinx_wagtail_theme/searchbox.html
sphinx_wagtail_theme/searchresults.html
sphinx_wagtail_theme/sitemap.html
sphinx_wagtail_theme/source-buttons.html
sphinx_wagtail_theme/theme.conf
sphinx_wagtail_theme/static/dist/blocking.js
sphinx_wagtail_theme/static/dist/blocking.js.map
sphinx_wagtail_theme/static/dist/fontawesome.css
sphinx_wagtail_theme/static/dist/fontawesome.css.map
sphinx_wagtail_theme/static/dist/fontawesome.js
sphinx_wagtail_theme/static/dist/theme.css
sphinx_wagtail_theme/static/dist/theme.css.map
sphinx_wagtail_theme/static/dist/theme.js
sphinx_wagtail_theme/static/dist/theme.js.map
sphinx_wagtail_theme/static/dist/vendor.js
sphinx_wagtail_theme/static/dist/vendor.js.LICENSE.txt
sphinx_wagtail_theme/static/dist/vendor.js.map
sphinx_wagtail_theme/static/dist/assets/fa-brands-400.eot
sphinx_wagtail_theme/static/dist/assets/fa-brands-400.svg
sphinx_wagtail_theme/static/dist/assets/fa-brands-400.ttf
sphinx_wagtail_theme/static/dist/assets/fa-brands-400.woff
sphinx_wagtail_theme/static/dist/assets/fa-brands-400.woff2
sphinx_wagtail_theme/static/dist/assets/fa-regular-400.eot
sphinx_wagtail_theme/static/dist/assets/fa-regular-400.svg
sphinx_wagtail_theme/static/dist/assets/fa-regular-400.ttf
sphinx_wagtail_theme/static/dist/assets/fa-regular-400.woff
sphinx_wagtail_theme/static/dist/assets/fa-regular-400.woff2
sphinx_wagtail_theme/static/dist/assets/fa-solid-900.eot
sphinx_wagtail_theme/static/dist/assets/fa-solid-900.svg
sphinx_wagtail_theme/static/dist/assets/fa-solid-900.ttf
sphinx_wagtail_theme-6.4.0.dist-info/LICENSE
sphinx_wagtail_theme-6.4.0.dist-info/METADATA
sphinx_wagtail_theme-6.4.0.dist-info/WHEEL
sphinx_wagtail_theme-6.4.0.dist-info/top_level.txt
sphinx_wagtail_theme-6.4.0.dist-info/RECORD
