Metadata-Version: 2.1
Name: sphinx_wagtail_theme
Version: 6.4.0
Summary: Sphinx Wagtail theme
Home-page: https://github.com/wagtail/sphinx_wagtail_theme
Author: Coen van der Kamp
Author-email: coen@fourdigits.nl
Project-URL: Bug Tracker, https://github.com/wagtail/sphinx_wagtail_theme/issues
Classifier: Framework :: Sphinx
Classifier: Framework :: Sphinx :: Theme
Classifier: Development Status :: 5 - Production/Stable
Classifier: License :: OSI Approved :: MIT License
Classifier: Intended Audience :: Developers
Classifier: Programming Language :: Python :: 3.8
Classifier: Programming Language :: Python :: 3.9
Classifier: Programming Language :: Python :: 3.10
Classifier: Programming Language :: Python :: 3.11
Classifier: Operating System :: OS Independent
Classifier: Topic :: Documentation
Classifier: Topic :: Software Development :: Documentation
Requires-Python: >=3.8
License-File: LICENSE
Requires-Dist: sphinx-copybutton
